phconvert/__init__.py
phconvert/_version.py
phconvert/bhreader.py
phconvert/hdf5.py
phconvert/loader.py
phconvert/metadata.py
phconvert/plotter.py
phconvert/pqreader.py
phconvert/smreader.py
phconvert/specs/photon-hdf5_specs.json
phconvert/v04/__init__.py
phconvert/v04/hdf5.py
phconvert/v04/metadata.py
phconvert/v04/specs/photon-hdf5_specs.json
phconvert-0.9.1.dist-info/LICENSE.txt
phconvert-0.9.1.dist-info/METADATA
phconvert-0.9.1.dist-info/WHEEL
phconvert-0.9.1.dist-info/top_level.txt
phconvert-0.9.1.dist-info/RECORD
