Metadata-Version: 2.1
Name: phconvert
Version: 0.9.1
Summary: Convert Beker&Hickl, PicoQuant and other formats to Photon-HDF5.
Author-email: Antonino Ingargiola <tritemio@gmail.com>, Paul David Harris <harripd@gmail.com>
Maintainer-email: Paul David Harris <harripd@gmail.com>
License: The MIT License (MIT)
Project-URL: Homepage, http://photon-hdf5.github.io/phconvert/
Project-URL: Documentation, https://phconvert.readthedocs.io/en/latest/
Project-URL: Repositories, https://github.com/Photon-HDF5/phconvert
Project-URL: Issues, https://github.com/Photon-HDF5/phconvert/issues
Keywords: single-molecule FRET,smFRET,biophysics,file-format,HDF5,Photon-HDF5
Classifier: Intended Audience :: Science/Research
Classifier: Operating System :: OS Independent
Classifier: Programming Language :: Python
Classifier: Programming Language :: Python :: 3.6
Classifier: Programming Language :: Python :: 3.7
Classifier: Programming Language :: Python :: 3.8
Classifier: Programming Language :: Python :: 3.9
Classifier: Programming Language :: Python :: 3.10
Classifier: Programming Language :: Python :: 3.11
Classifier: Topic :: Scientific/Engineering
Requires-Python: >=3.6
License-File: LICENSE.txt
Requires-Dist: numpy>=1.19
Requires-Dist: tables
Requires-Dist: importlib_resources; python_version <= "3.10"
